scratchpad/__init__.py
scratchpad/__main__.py
scratchpad/scratchpad.py
scratchpad_deadmund-1.1.0.dist-info/LICENSE
scratchpad_deadmund-1.1.0.dist-info/METADATA
scratchpad_deadmund-1.1.0.dist-info/WHEEL
scratchpad_deadmund-1.1.0.dist-info/entry_points.txt
scratchpad_deadmund-1.1.0.dist-info/top_level.txt
scratchpad_deadmund-1.1.0.dist-info/RECORD
