Metadata-Version: 2.1
Name: scratchpad-deadmund
Version: 1.1.0
Summary: Notepad with basic math functions
Home-page: https://github.com/fmresearchnovak/scratchpad
Author: Ed Novak
Author-email: enovak@fandm.edu
License: UNKNOWN
Platform: UNKNOWN
Classifier: Programming Language :: Python :: 3
Classifier: License :: OSI Approved :: GNU General Public License v3 (GPLv3)
Classifier: Operating System :: OS Independent
